{"rows":[{"d":"2026-07-10","dow":"Fri","h":18,"v":240,"p":5,"b":0,"ltr":165,"rtl":80,"u":0.37},{"d":"2026-07-10","dow":"Fri","h":19,"v":734,"p":12,"b":0,"ltr":433,"rtl":313,"u":1.0},{"d":"2026-07-10","dow":"Fri","h":20,"v":683,"p":15,"b":0,"ltr":373,"rtl":325,"u":1.0},{"d":"2026-07-10","dow":"Fri","h":21,"v":352,"p":8,"b":0,"ltr":150,"rtl":210,"u":1.0},{"d":"2026-07-10","dow":"Fri","h":22,"v":32,"p":0,"b":0,"ltr":4,"rtl":28,"u":0.2},{"d":"2026-07-10","dow":"Fri","h":23,"v":0,"p":0,"b":0,"ltr":0,"rtl":0,"u":0},{"d":"2026-07-11","dow":"Sat","h":0,"v":0,"p":0,"b":0,"ltr":0,"rtl":0,"u":0},{"d":"2026-07-11","dow":"Sat","h":1,"v":18,"p":0,"b":0,"ltr":1,"rtl":17,"u":0.43},{"d":"2026-07-11","dow":"Sat","h":2,"v":57,"p":1,"b":0,"ltr":0,"rtl":58,"u":1.0},{"d":"2026-07-11","dow":"Sat","h":3,"v":31,"p":0,"b":0,"ltr":0,"rtl":31,"u":1.0},{"d":"2026-07-11","dow":"Sat","h":4,"v":26,"p":0,"b":0,"ltr":0,"rtl":26,"u":1.0},{"d":"2026-07-11","dow":"Sat","h":5,"v":24,"p":0,"b":0,"ltr":1,"rtl":23,"u":1.0},{"d":"2026-07-11","dow":"Sat","h":6,"v":213,"p":0,"b":0,"ltr":114,"rtl":99,"u":1.0},{"d":"2026-07-11","dow":"Sat","h":7,"v":313,"p":4,"b":0,"ltr":161,"rtl":156,"u":1.0},{"d":"2026-07-11","dow":"Sat","h":8,"v":372,"p":7,"b":0,"ltr":190,"rtl":189,"u":1.0},{"d":"2026-07-11","dow":"Sat","h":9,"v":551,"p":4,"b":0,"ltr":305,"rtl":250,"u":1.0},{"d":"2026-07-11","dow":"Sat","h":10,"v":628,"p":2,"b":0,"ltr":363,"rtl":267,"u":1.0},{"d":"2026-07-11","dow":"Sat","h":11,"v":677,"p":7,"b":1,"ltr":383,"rtl":302,"u":1.0},{"d":"2026-07-11","dow":"Sat","h":12,"v":692,"p":9,"b":0,"ltr":407,"rtl":294,"u":1.0},{"d":"2026-07-11","dow":"Sat","h":13,"v":673,"p":10,"b":0,"ltr":381,"rtl":302,"u":1.0},{"d":"2026-07-11","dow":"Sat","h":14,"v":754,"p":9,"b":0,"ltr":432,"rtl":331,"u":1.0},{"d":"2026-07-11","dow":"Sat","h":15,"v":725,"p":9,"b":0,"ltr":391,"rtl":343,"u":1.0},{"d":"2026-07-11","dow":"Sat","h":16,"v":757,"p":18,"b":0,"ltr":415,"rtl":360,"u":1.0},{"d":"2026-07-11","dow":"Sat","h":17,"v":703,"p":14,"b":0,"ltr":443,"rtl":274,"u":1.0},{"d":"2026-07-11","dow":"Sat","h":18,"v":696,"p":7,"b":0,"ltr":389,"rtl":314,"u":1.0},{"d":"2026-07-11","dow":"Sat","h":19,"v":653,"p":18,"b":1,"ltr":378,"rtl":294,"u":1.0},{"d":"2026-07-11","dow":"Sat","h":20,"v":647,"p":14,"b":0,"ltr":366,"rtl":295,"u":1.0},{"d":"2026-07-11","dow":"Sat","h":21,"v":394,"p":9,"b":0,"ltr":201,"rtl":202,"u":1.0},{"d":"2026-07-11","dow":"Sat","h":22,"v":115,"p":0,"b":0,"ltr":13,"rtl":102,"u":1.0},{"d":"2026-07-11","dow":"Sat","h":23,"v":101,"p":1,"b":0,"ltr":3,"rtl":99,"u":1.0},{"d":"2026-07-12","dow":"Sun","h":0,"v":68,"p":0,"b":0,"ltr":7,"rtl":61,"u":1.0},{"d":"2026-07-12","dow":"Sun","h":1,"v":37,"p":1,"b":0,"ltr":3,"rtl":35,"u":1.0},{"d":"2026-07-12","dow":"Sun","h":2,"v":44,"p":0,"b":0,"ltr":0,"rtl":44,"u":1.0},{"d":"2026-07-12","dow":"Sun","h":3,"v":22,"p":0,"b":0,"ltr":0,"rtl":22,"u":1.0},{"d":"2026-07-12","dow":"Sun","h":4,"v":19,"p":0,"b":0,"ltr":0,"rtl":19,"u":1.0},{"d":"2026-07-12","dow":"Sun","h":5,"v":31,"p":0,"b":0,"ltr":9,"rtl":22,"u":1.0},{"d":"2026-07-12","dow":"Sun","h":6,"v":175,"p":1,"b":0,"ltr":111,"rtl":65,"u":1.0},{"d":"2026-07-12","dow":"Sun","h":7,"v":208,"p":7,"b":0,"ltr":110,"rtl":105,"u":1.0},{"d":"2026-07-12","dow":"Sun","h":8,"v":304,"p":5,"b":0,"ltr":181,"rtl":128,"u":1.0},{"d":"2026-07-12","dow":"Sun","h":9,"v":456,"p":4,"b":0,"ltr":276,"rtl":184,"u":1.0},{"d":"2026-07-12","dow":"Sun","h":10,"v":535,"p":7,"b":0,"ltr":320,"rtl":222,"u":1.0},{"d":"2026-07-12","dow":"Sun","h":11,"v":605,"p":10,"b":0,"ltr":382,"rtl":233,"u":1.0},{"d":"2026-07-12","dow":"Sun","h":12,"v":734,"p":2,"b":0,"ltr":451,"rtl":285,"u":1.0},{"d":"2026-07-12","dow":"Sun","h":13,"v":711,"p":11,"b":0,"ltr":387,"rtl":335,"u":1.0},{"d":"2026-07-12","dow":"Sun","h":14,"v":695,"p":7,"b":0,"ltr":425,"rtl":277,"u":1.0},{"d":"2026-07-12","dow":"Sun","h":15,"v":620,"p":13,"b":0,"ltr":382,"rtl":251,"u":1.0},{"d":"2026-07-12","dow":"Sun","h":16,"v":687,"p":7,"b":0,"ltr":403,"rtl":291,"u":1.0},{"d":"2026-07-12","dow":"Sun","h":17,"v":740,"p":14,"b":0,"ltr":420,"rtl":334,"u":1.0},{"d":"2026-07-12","dow":"Sun","h":18,"v":735,"p":17,"b":0,"ltr":458,"rtl":294,"u":1.0},{"d":"2026-07-12","dow":"Sun","h":19,"v":624,"p":13,"b":2,"ltr":380,"rtl":259,"u":1.0},{"d":"2026-07-12","dow":"Sun","h":20,"v":529,"p":12,"b":0,"ltr":320,"rtl":221,"u":1.0},{"d":"2026-07-12","dow":"Sun","h":21,"v":327,"p":16,"b":0,"ltr":164,"rtl":179,"u":1.0},{"d":"2026-07-12","dow":"Sun","h":22,"v":84,"p":1,"b":0,"ltr":5,"rtl":80,"u":1.0},{"d":"2026-07-12","dow":"Sun","h":23,"v":67,"p":0,"b":0,"ltr":1,"rtl":66,"u":1.0},{"d":"2026-07-13","dow":"Mon","h":0,"v":36,"p":0,"b":0,"ltr":1,"rtl":35,"u":1.0},{"d":"2026-07-13","dow":"Mon","h":1,"v":21,"p":0,"b":0,"ltr":1,"rtl":20,"u":1.0},{"d":"2026-07-13","dow":"Mon","h":2,"v":20,"p":0,"b":0,"ltr":1,"rtl":19,"u":1.0},{"d":"2026-07-13","dow":"Mon","h":3,"v":20,"p":0,"b":0,"ltr":1,"rtl":19,"u":1.0},{"d":"2026-07-13","dow":"Mon","h":4,"v":24,"p":0,"b":0,"ltr":1,"rtl":23,"u":1.0},{"d":"2026-07-13","dow":"Mon","h":5,"v":73,"p":0,"b":0,"ltr":26,"rtl":47,"u":1.0},{"d":"2026-07-13","dow":"Mon","h":6,"v":553,"p":2,"b":0,"ltr":351,"rtl":204,"u":1.0},{"d":"2026-07-13","dow":"Mon","h":7,"v":755,"p":3,"b":0,"ltr":480,"rtl":278,"u":0.99},{"d":"2026-07-13","dow":"Mon","h":8,"v":0,"p":0,"b":0,"ltr":0,"rtl":0,"u":0},{"d":"2026-07-13","dow":"Mon","h":9,"v":0,"p":0,"b":0,"ltr":0,"rtl":0,"u":0},{"d":"2026-07-13","dow":"Mon","h":10,"v":0,"p":0,"b":0,"ltr":0,"rtl":0,"u":0},{"d":"2026-07-13","dow":"Mon","h":11,"v":0,"p":0,"b":0,"ltr":0,"rtl":0,"u":0},{"d":"2026-07-13","dow":"Mon","h":12,"v":627,"p":4,"b":0,"ltr":383,"rtl":248,"u":0.89},{"d":"2026-07-13","dow":"Mon","h":13,"v":716,"p":9,"b":0,"ltr":440,"rtl":285,"u":1.0},{"d":"2026-07-13","dow":"Mon","h":14,"v":799,"p":6,"b":0,"ltr":464,"rtl":341,"u":1.0},{"d":"2026-07-13","dow":"Mon","h":15,"v":851,"p":4,"b":0,"ltr":448,"rtl":407,"u":1.0},{"d":"2026-07-13","dow":"Mon","h":16,"v":983,"p":12,"b":0,"ltr":536,"rtl":459,"u":1.0},{"d":"2026-07-13","dow":"Mon","h":17,"v":989,"p":4,"b":0,"ltr":590,"rtl":403,"u":1.0},{"d":"2026-07-13","dow":"Mon","h":18,"v":835,"p":2,"b":0,"ltr":439,"rtl":398,"u":1.0},{"d":"2026-07-13","dow":"Mon","h":19,"v":664,"p":7,"b":0,"ltr":340,"rtl":331,"u":1.0},{"d":"2026-07-13","dow":"Mon","h":20,"v":574,"p":5,"b":0,"ltr":320,"rtl":259,"u":1.0}],"classes":{"car":28709,"truck":629,"person":389,"bus":83,"motorcycle":37,"bicycle":4},"spdByHour":[121,120,115,115,127,126,72,66,67,66,64,64,66,60,68,68,64,60,57,62,61,111,114,114],"dirByHour":[[4.0,48.0],[2.0,27.5],[0.3,40.3],[0.3,24.0],[0.3,22.7],[12.0,30.7],[192.0,122.7],[250.3,179.7],[185.5,158.5],[290.5,217.0],[341.5,244.5],[382.5,267.5],[429.0,289.5],[402.7,307.3],[440.3,316.3],[407.0,333.7],[451.3,370.0],[484.3,337.0],[428.7,335.3],[382.8,299.2],[344.8,275.0],[171.7,197.0],[9.0,91.0],[2.0,82.5]],"nFullByHour":[2,2,3,3,3,3,3,3,2,2,2,2,2,3,3,3,3,3,3,4,4,3,2,2]}